Metadata-Version: 2.1
Name: facturapi
Version: 1.0.0
Summary: Facturapi API Client
Home-page: https://github.com/cuenca-mx/facturapi-python
Author: Cuenca
Author-email: dev@cuenca.com
Classifier: Programming Language :: Python :: 3
Classifier: Programming Language :: Python :: 3.10
Classifier: Programming Language :: Python :: 3.11
Classifier: Programming Language :: Python :: 3.12
Classifier: Programming Language :: Python :: 3.13
Classifier: License :: OSI Approved :: MIT License
Classifier: Operating System :: OS Independent
Requires-Python: >=3.10
License-File: LICENSE
Requires-Dist: httpx<1.0.0,>=0.28.0
Requires-Dist: pydantic<3.0.0,>=2.10.0
